{
  "id": "0561aab2-47b9-4891-bd9e-fd56e955c875",
  "realm": "sealAI",
  "notBefore": 0,
  "defaultSignatureAlgorithm": "RS256",
  "revokeRefreshToken": false,
  "refreshTokenMaxReuse": 0,
  "accessTokenLifespan": 300,
  "accessTokenLifespanForImplicitFlow": 900,
  "ssoSessionIdleTimeout": 1800,
  "ssoSessionMaxLifespan": 36000,
  "ssoSessionIdleTimeoutRememberMe": 0,
  "ssoSessionMaxLifespanRememberMe": 0,
  "offlineSessionIdleTimeout": 2592000,
  "offlineSessionMaxLifespanEnabled": false,
  "offlineSessionMaxLifespan": 5184000,
  "clientSessionIdleTimeout": 0,
  "clientSessionMaxLifespan": 0,
  "clientOfflineSessionIdleTimeout": 0,
  "clientOfflineSessionMaxLifespan": 0,
  "accessCodeLifespan": 60,
  "accessCodeLifespanUserAction": 300,
  "accessCodeLifespanLogin": 1800,
  "actionTokenGeneratedByAdminLifespan": 43200,
  "actionTokenGeneratedByUserLifespan": 300,
  "oauth2DeviceCodeLifespan": 600,
  "oauth2DevicePollingInterval": 5,
  "enabled": true,
  "sslRequired": "external",
  "registrationAllowed": true,
  "registrationEmailAsUsername": false,
  "rememberMe": true,
  "verifyEmail": false,
  "loginWithEmailAllowed": true,
  "duplicateEmailsAllowed": false,
  "resetPasswordAllowed": true,
  "editUsernameAllowed": false,
  "bruteForceProtected": false,
  "permanentLockout": false,
  "maxTemporaryLockouts": 0,
  "maxFailureWaitSeconds": 900,
  "minimumQuickLoginWaitSeconds": 60,
  "waitIncrementSeconds": 60,
  "quickLoginCheckMilliSeconds": 1000,
  "maxDeltaTimeSeconds": 43200,
  "failureFactor": 30,
  "roles": {
    "realm": [
      {
        "id": "98e40673-783a-48cf-8e2f-6cad320306c5",
        "name": "default-roles-sealai",
        "description": "${role_default-roles}",
        "composite": true,
        "composites": {
          "realm": [
            "offline_access",
            "uma_authorization"
          ],
          "client": {
            "account": [
              "manage-account",
              "view-profile"
            ]
          }
        },
        "clientRole": false,
        "containerId": "0561aab2-47b9-4891-bd9e-fd56e955c875",
        "attributes": {}
      },
      {
        "id": "80b9c868-c780-4e67-84b5-88a3dd315595",
        "name": "uma_authorization",
        "description": "${role_uma_authorization}",
        "composite": false,
        "clientRole": false,
        "containerId": "0561aab2-47b9-4891-bd9e-fd56e955c875",
        "attributes": {}
      },
      {
        "id": "60420c4f-bd6e-438c-85e2-524f4b6663b0",
        "name": "offline_access",
        "description": "${role_offline-access}",
        "composite": false,
        "clientRole": false,
        "containerId": "0561aab2-47b9-4891-bd9e-fd56e955c875",
        "attributes": {}
      }
    ],
    "client": {
      "realm-management": [
        {
          "id": "127ef247-31b4-4767-9d77-afc613fac671",
          "name": "view-realm",
          "description": "${role_view-realm}",
          "composite": false,
          "clientRole": true,
          "containerId": "d20f116f-498b-4fc2-9437-9a8dd262c1e1",
          "attributes": {}
        },
        {
          "id": "811512fa-7313-4b49-a2fa-480c960f1e63",
          "name": "view-users",
          "description": "${role_view-users}",
          "composite": true,
          "composites": {
            "client": {
              "realm-management": [
                "query-groups",
                "query-users"
              ]
            }
          },
          "clientRole": true,
          "containerId": "d20f116f-498b-4fc2-9437-9a8dd262c1e1",
          "attributes": {}
        },
        {
          "id": "a326ef38-38e9-48ab-b8ea-b9419a4ab6b2",
          "name": "query-groups",
          "description": "${role_query-groups}",
          "composite": false,
          "clientRole": true,
          "containerId": "d20f116f-498b-4fc2-9437-9a8dd262c1e1",
          "attributes": {}
        },
        {
          "id": "f1396b8c-a0dd-44aa-b983-181e4f1a96ca",
          "name": "query-users",
          "description": "${role_query-users}",
          "composite": false,
          "clientRole": true,
          "containerId": "d20f116f-498b-4fc2-9437-9a8dd262c1e1",
          "attributes": {}
        },
        {
          "id": "c642225e-f360-4aef-ab4d-3759c4d05482",
          "name": "impersonation",
          "description": "${role_impersonation}",
          "composite": false,
          "clientRole": true,
          "containerId": "d20f116f-498b-4fc2-9437-9a8dd262c1e1",
          "attributes": {}
        },
        {
          "id": "2e540bae-15c6-448f-b05d-b86c81d9b520",
          "name": "manage-identity-providers",
          "description": "${role_manage-identity-providers}",
          "composite": false,
          "clientRole": true,
          "containerId": "d20f116f-498b-4fc2-9437-9a8dd262c1e1",
          "attributes": {}
        },
        {
          "id": "5daa8e85-764c-4878-a14c-10b65cecdec2",
          "name": "view-events",
          "description": "${role_view-events}",
          "composite": false,
          "clientRole": true,
          "containerId": "d20f116f-498b-4fc2-9437-9a8dd262c1e1",
          "attributes": {}
        },
        {
          "id": "2ca92b86-eb7c-40fc-98d3-3c262b334cd0",
          "name": "view-authorization",
          "description": "${role_view-authorization}",
          "composite": false,
          "clientRole": true,
          "containerId": "d20f116f-498b-4fc2-9437-9a8dd262c1e1",
          "attributes": {}
        },
        {
          "id": "00abfaf4-2d6c-49b9-bb7f-f7291aa931e0",
          "name": "manage-clients",
          "description": "${role_manage-clients}",
          "composite": false,
          "clientRole": true,
          "containerId": "d20f116f-498b-4fc2-9437-9a8dd262c1e1",
          "attributes": {}
        },
        {
          "id": "9ca61856-5eef-48e6-b15f-b7100d13bd85",
          "name": "manage-realm",
          "description": "${role_manage-realm}",
          "composite": false,
          "clientRole": true,
          "containerId": "d20f116f-498b-4fc2-9437-9a8dd262c1e1",
          "attributes": {}
        },
        {
          "id": "9d1eb58a-6c67-4eb2-8269-00d75c8e13ee",
          "name": "manage-authorization",
          "description": "${role_manage-authorization}",
          "composite": false,
          "clientRole": true,
          "containerId": "d20f116f-498b-4fc2-9437-9a8dd262c1e1",
          "attributes": {}
        },
        {
          "id": "c2ccf125-2b46-49ea-aba9-e2107fe63ffa",
          "name": "view-identity-providers",
          "description": "${role_view-identity-providers}",
          "composite": false,
          "clientRole": true,
          "containerId": "d20f116f-498b-4fc2-9437-9a8dd262c1e1",
          "attributes": {}
        },
        {
          "id": "f7767abf-ef5b-4736-ab64-b7c6c95409a1",
          "name": "realm-admin",
          "description": "${role_realm-admin}",
          "composite": true,
          "composites": {
            "client": {
              "realm-management": [
                "view-realm",
                "view-users",
                "query-groups",
                "query-users",
                "impersonation",
                "manage-identity-providers",
                "view-events",
                "view-authorization",
                "manage-realm",
                "manage-clients",
                "view-identity-providers",
                "manage-authorization",
                "create-client",
                "manage-events",
                "query-clients",
                "manage-users",
                "query-realms",
                "view-clients"
              ]
            }
          },
          "clientRole": true,
          "containerId": "d20f116f-498b-4fc2-9437-9a8dd262c1e1",
          "attributes": {}
        },
        {
          "id": "1b716acc-c641-480c-a299-b4af62f02473",
          "name": "create-client",
          "description": "${role_create-client}",
          "composite": false,
          "clientRole": true,
          "containerId": "d20f116f-498b-4fc2-9437-9a8dd262c1e1",
          "attributes": {}
        },
        {
          "id": "5d6c57ab-cbf9-4949-b00a-dde48a14f54f",
          "name": "manage-events",
          "description": "${role_manage-events}",
          "composite": false,
          "clientRole": true,
          "containerId": "d20f116f-498b-4fc2-9437-9a8dd262c1e1",
          "attributes": {}
        },
        {
          "id": "30fc0c06-5003-462a-bfe3-1815798c694a",
          "name": "query-clients",
          "description": "${role_query-clients}",
          "composite": false,
          "clientRole": true,
          "containerId": "d20f116f-498b-4fc2-9437-9a8dd262c1e1",
          "attributes": {}
        },
        {
          "id": "09c9fe0d-6c9d-4ec9-8c17-2fad33915db3",
          "name": "manage-users",
          "description": "${role_manage-users}",
          "composite": false,
          "clientRole": true,
          "containerId": "d20f116f-498b-4fc2-9437-9a8dd262c1e1",
          "attributes": {}
        },
        {
          "id": "ccd37189-04ab-4d7c-9961-96466c8c7044",
          "name": "query-realms",
          "description": "${role_query-realms}",
          "composite": false,
          "clientRole": true,
          "containerId": "d20f116f-498b-4fc2-9437-9a8dd262c1e1",
          "attributes": {}
        },
        {
          "id": "3a332a43-f26c-469c-9d0e-7289a2271cf7",
          "name": "view-clients",
          "description": "${role_view-clients}",
          "composite": true,
          "composites": {
            "client": {
              "realm-management": [
                "query-clients"
              ]
            }
          },
          "clientRole": true,
          "containerId": "d20f116f-498b-4fc2-9437-9a8dd262c1e1",
          "attributes": {}
        }
      ],
      "security-admin-console": [],
      "nextauth": [],
      "admin-cli": [],
      "account-console": [],
      "broker": [
        {
          "id": "45d06e4a-6451-43a3-8f65-b848e3179c14",
          "name": "read-token",
          "description": "${role_read-token}",
          "composite": false,
          "clientRole": true,
          "containerId": "fc0c8288-cbc6-43f5-a9dd-7401d8de6e7c",
          "attributes": {}
        }
      ],
      "account": [
        {
          "id": "2def2f21-1da6-45f8-8305-7581330cc1b3",
          "name": "delete-account",
          "description": "${role_delete-account}",
          "composite": false,
          "clientRole": true,
          "containerId": "8355be9d-35f4-4baa-a45c-a5549056fbea",
          "attributes": {}
        },
        {
          "id": "2ec42c9f-9cc7-4162-a1f3-b8b7617d8b4a",
          "name": "manage-account",
          "description": "${role_manage-account}",
          "composite": true,
          "composites": {
            "client": {
              "account": [
                "manage-account-links"
              ]
            }
          },
          "clientRole": true,
          "containerId": "8355be9d-35f4-4baa-a45c-a5549056fbea",
          "attributes": {}
        },
        {
          "id": "c77c9691-09ab-4d2c-afdf-012224f7c334",
          "name": "view-consent",
          "description": "${role_view-consent}",
          "composite": false,
          "clientRole": true,
          "containerId": "8355be9d-35f4-4baa-a45c-a5549056fbea",
          "attributes": {}
        },
        {
          "id": "5c88ce71-5a9a-4d69-bb7b-e2643cf388aa",
          "name": "view-groups",
          "description": "${role_view-groups}",
          "composite": false,
          "clientRole": true,
          "containerId": "8355be9d-35f4-4baa-a45c-a5549056fbea",
          "attributes": {}
        },
        {
          "id": "09236dbb-02d9-4534-ae34-424ee207addd",
          "name": "view-applications",
          "description": "${role_view-applications}",
          "composite": false,
          "clientRole": true,
          "containerId": "8355be9d-35f4-4baa-a45c-a5549056fbea",
          "attributes": {}
        },
        {
          "id": "79a47428-1cfb-4ab1-b2b7-210970a238ee",
          "name": "view-profile",
          "description": "${role_view-profile}",
          "composite": false,
          "clientRole": true,
          "containerId": "8355be9d-35f4-4baa-a45c-a5549056fbea",
          "attributes": {}
        },
        {
          "id": "282df607-400b-449c-80d6-279da5056b55",
          "name": "manage-account-links",
          "description": "${role_manage-account-links}",
          "composite": false,
          "clientRole": true,
          "containerId": "8355be9d-35f4-4baa-a45c-a5549056fbea",
          "attributes": {}
        },
        {
          "id": "031f67de-ca06-4dd9-bc30-1ea76fde5b66",
          "name": "manage-consent",
          "description": "${role_manage-consent}",
          "composite": true,
          "composites": {
            "client": {
              "account": [
                "view-consent"
              ]
            }
          },
          "clientRole": true,
          "containerId": "8355be9d-35f4-4baa-a45c-a5549056fbea",
          "attributes": {}
        }
      ]
    }
  },
  "groups": [],
  "defaultRole": {
    "id": "98e40673-783a-48cf-8e2f-6cad320306c5",
    "name": "default-roles-sealai",
    "description": "${role_default-roles}",
    "composite": true,
    "clientRole": false,
    "containerId": "0561aab2-47b9-4891-bd9e-fd56e955c875"
  },
  "requiredCredentials": [
    "password"
  ],
  "otpPolicyType": "totp",
  "otpPolicyAlgorithm": "HmacSHA1",
  "otpPolicyInitialCounter": 0,
  "otpPolicyDigits": 6,
  "otpPolicyLookAheadWindow": 1,
  "otpPolicyPeriod": 30,
  "otpPolicyCodeReusable": false,
  "otpSupportedApplications": [
    "totpAppFreeOTPName",
    "totpAppGoogleName",
    "totpAppMicrosoftAuthenticatorName"
  ],
  "localizationTexts": {},
  "webAuthnPolicyRpEntityName": "keycloak",
  "webAuthnPolicySignatureAlgorithms": [
    "ES256"
  ],
  "webAuthnPolicyRpId": "",
  "webAuthnPolicyAttestationConveyancePreference": "not specified",
  "webAuthnPolicyAuthenticatorAttachment": "not specified",
  "webAuthnPolicyRequireResidentKey": "not specified",
  "webAuthnPolicyUserVerificationRequirement": "not specified",
  "webAuthnPolicyCreateTimeout": 0,
  "webAuthnPolicyAvoidSameAuthenticatorRegister": false,
  "webAuthnPolicyAcceptableAaguids": [],
  "webAuthnPolicyExtraOrigins": [],
  "webAuthnPolicyPasswordlessRpEntityName": "keycloak",
  "webAuthnPolicyPasswordlessSignatureAlgorithms": [
    "ES256"
  ],
  "webAuthnPolicyPasswordlessRpId": "",
  "webAuthnPolicyPasswordlessAttestationConveyancePreference": "not specified",
  "webAuthnPolicyPasswordlessAuthenticatorAttachment": "not specified",
  "webAuthnPolicyPasswordlessRequireResidentKey": "not specified",
  "webAuthnPolicyPasswordlessUserVerificationRequirement": "not specified",
  "webAuthnPolicyPasswordlessCreateTimeout": 0,
  "webAuthnPolicyPasswordlessAvoidSameAuthenticatorRegister": false,
  "webAuthnPolicyPasswordlessAcceptableAaguids": [],
  "webAuthnPolicyPasswordlessExtraOrigins": [],
  "scopeMappings": [
    {
      "clientScope": "offline_access",
      "roles": [
        "offline_access"
      ]
    }
  ],
  "clientScopeMappings": {
    "account": [
      {
        "client": "account-console",
        "roles": [
          "manage-account",
          "view-groups"
        ]
      }
    ]
  },
  "clients": [
    {
      "id": "8355be9d-35f4-4baa-a45c-a5549056fbea",
      "clientId": "account",
      "name": "${client_account}",
      "rootUrl": "${authBaseUrl}",
      "baseUrl": "/realms/sealAI/account/",
      "surrogateAuthRequired": false,
      "enabled": true,
      "alwaysDisplayInConsole": false,
      "clientAuthenticatorType": "client-secret",
      "redirectUris": [
        "/realms/sealAI/account/*"
      ],
      "webOrigins": [],
      "notBefore": 0,
      "bearerOnly": false,
      "consentRequired": false,
      "standardFlowEnabled": true,
      "implicitFlowEnabled": false,
      "directAccessGrantsEnabled": false,
      "serviceAccountsEnabled": false,
      "publicClient": true,
      "frontchannelLogout": false,
      "protocol": "openid-connect",
      "attributes": {
        "post.logout.redirect.uris": "+"
      },
      "authenticationFlowBindingOverrides": {},
      "fullScopeAllowed": false,
      "nodeReRegistrationTimeout": 0,
      "defaultClientScopes": [
        "web-origins",
        "acr",
        "profile",
        "roles",
        "email"
      ],
      "optionalClientScopes": [
        "address",
        "phone",
        "offline_access",
        "microprofile-jwt"
      ]
    },
    {
      "id": "3dce021f-1f34-4ba4-86d1-031ecba8a035",
      "clientId": "account-console",
      "name": "${client_account-console}",
      "rootUrl": "${authBaseUrl}",
      "baseUrl": "/realms/sealAI/account/",
      "surrogateAuthRequired": false,
      "enabled": true,
      "alwaysDisplayInConsole": false,
      "clientAuthenticatorType": "client-secret",
      "redirectUris": [
        "/realms/sealAI/account/*"
      ],
      "webOrigins": [],
      "notBefore": 0,
      "bearerOnly": false,
      "consentRequired": false,
      "standardFlowEnabled": true,
      "implicitFlowEnabled": false,
      "directAccessGrantsEnabled": false,
      "serviceAccountsEnabled": false,
      "publicClient": true,
      "frontchannelLogout": false,
      "protocol": "openid-connect",
      "attributes": {
        "post.logout.redirect.uris": "+",
        "pkce.code.challenge.method": "S256"
      },
      "authenticationFlowBindingOverrides": {},
      "fullScopeAllowed": false,
      "nodeReRegistrationTimeout": 0,
      "protocolMappers": [
        {
          "id": "c8b966bc-9ccf-4f2a-9aa6-59e71aed69ef",
          "name": "audience resolve",
          "protocol": "openid-connect",
          "protocolMapper": "oidc-audience-resolve-mapper",
          "consentRequired": false,
          "config": {}
        }
      ],
      "defaultClientScopes": [
        "web-origins",
        "acr",
        "profile",
        "roles",
        "email"
      ],
      "optionalClientScopes": [
        "address",
        "phone",
        "offline_access",
        "microprofile-jwt"
      ]
    },
    {
      "id": "7747342e-fb35-4c43-86e4-a9b0c5cb2922",
      "clientId": "admin-cli",
      "name": "${client_admin-cli}",
      "surrogateAuthRequired": false,
      "enabled": true,
      "alwaysDisplayInConsole": false,
      "clientAuthenticatorType": "client-secret",
      "redirectUris": [],
      "webOrigins": [],
      "notBefore": 0,
      "bearerOnly": false,
      "consentRequired": false,
      "standardFlowEnabled": false,
      "implicitFlowEnabled": false,
      "directAccessGrantsEnabled": true,
      "serviceAccountsEnabled": false,
      "publicClient": true,
      "frontchannelLogout": false,
      "protocol": "openid-connect",
      "attributes": {},
      "authenticationFlowBindingOverrides": {},
      "fullScopeAllowed": false,
      "nodeReRegistrationTimeout": 0,
      "defaultClientScopes": [
        "web-origins",
        "acr",
        "profile",
        "roles",
        "email"
      ],
      "optionalClientScopes": [
        "address",
        "phone",
        "offline_access",
        "microprofile-jwt"
      ]
    },
    {
      "id": "fc0c8288-cbc6-43f5-a9dd-7401d8de6e7c",
      "clientId": "broker",
      "name": "${client_broker}",
      "surrogateAuthRequired": false,
      "enabled": true,
      "alwaysDisplayInConsole": false,
      "clientAuthenticatorType": "client-secret",
      "redirectUris": [],
      "webOrigins": [],
      "notBefore": 0,
      "bearerOnly": true,
      "consentRequired": false,
      "standardFlowEnabled": true,
      "implicitFlowEnabled": false,
      "directAccessGrantsEnabled": false,
      "serviceAccountsEnabled": false,
      "publicClient": false,
      "frontchannelLogout": false,
      "protocol": "openid-connect",
      "attributes": {},
      "authenticationFlowBindingOverrides": {},
      "fullScopeAllowed": false,
      "nodeReRegistrationTimeout": 0,
      "defaultClientScopes": [
        "web-origins",
        "acr",
        "profile",
        "roles",
        "email"
      ],
      "optionalClientScopes": [
        "address",
        "phone",
        "offline_access",
        "microprofile-jwt"
      ]
    },
    {
      "id": "c9267ac2-a7dc-4a62-ba11-25d932a8f8a2",
      "clientId": "nextauth",
      "name": "",
      "description": "",
      "rootUrl": "https://sealai.net",
      "adminUrl": "",
      "baseUrl": "https://sealai.net",
      "surrogateAuthRequired": false,
      "enabled": true,
      "alwaysDisplayInConsole": false,
      "clientAuthenticatorType": "client-secret",
      "redirectUris": [
        "https://sealai.net/*"
      ],
      "webOrigins": [
        "https://sealai.net"
      ],
      "notBefore": 0,
      "bearerOnly": false,
      "consentRequired": false,
      "standardFlowEnabled": true,
      "implicitFlowEnabled": false,
      "directAccessGrantsEnabled": true,
      "serviceAccountsEnabled": false,
      "publicClient": true,
      "frontchannelLogout": true,
      "protocol": "openid-connect",
      "attributes": {
        "oidc.ciba.grant.enabled": "false",
        "client.secret.creation.time": "1742978527",
        "backchannel.logout.session.required": "true",
        "post.logout.redirect.uris": "https://sealai.net/login##https://sealai.net##https://sealai.net/logout##https://sealai.net/api/auth/logout",
        "display.on.consent.screen": "false",
        "oauth2.device.authorization.grant.enabled": "false",
        "backchannel.logout.revoke.offline.tokens": "false"
      },
      "authenticationFlowBindingOverrides": {},
      "fullScopeAllowed": true,
      "nodeReRegistrationTimeout": -1,
      "defaultClientScopes": [
        "web-origins",
        "acr",
        "profile",
        "roles",
        "email"
      ],
      "optionalClientScopes": [
        "address",
        "phone",
        "offline_access",
        "microprofile-jwt"
      ]
    },
    {
      "id": "d20f116f-498b-4fc2-9437-9a8dd262c1e1",
      "clientId": "realm-management",
      "name": "${client_realm-management}",
      "surrogateAuthRequired": false,
      "enabled": true,
      "alwaysDisplayInConsole": false,
      "clientAuthenticatorType": "client-secret",
      "redirectUris": [],
      "webOrigins": [],
      "notBefore": 0,
      "bearerOnly": true,
      "consentRequired": false,
      "standardFlowEnabled": true,
      "implicitFlowEnabled": false,
      "directAccessGrantsEnabled": false,
      "serviceAccountsEnabled": false,
      "publicClient": false,
      "frontchannelLogout": false,
      "protocol": "openid-connect",
      "attributes": {},
      "authenticationFlowBindingOverrides": {},
      "fullScopeAllowed": false,
      "nodeReRegistrationTimeout": 0,
      "defaultClientScopes": [
        "web-origins",
        "acr",
        "profile",
        "roles",
        "email"
      ],
      "optionalClientScopes": [
        "address",
        "phone",
        "offline_access",
        "microprofile-jwt"
      ]
    },
    {
      "id": "8c362455-da79-4841-a437-29dc09089395",
      "clientId": "security-admin-console",
      "name": "${client_security-admin-console}",
      "rootUrl": "${authAdminUrl}",
      "baseUrl": "/admin/sealAI/console/",
      "surrogateAuthRequired": false,
      "enabled": true,
      "alwaysDisplayInConsole": false,
      "clientAuthenticatorType": "client-secret",
      "redirectUris": [
        "/admin/sealAI/console/*"
      ],
      "webOrigins": [
        "+"
      ],
      "notBefore": 0,
      "bearerOnly": false,
      "consentRequired": false,
      "standardFlowEnabled": true,
      "implicitFlowEnabled": false,
      "directAccessGrantsEnabled": false,
      "serviceAccountsEnabled": false,
      "publicClient": true,
      "frontchannelLogout": false,
      "protocol": "openid-connect",
      "attributes": {
        "post.logout.redirect.uris": "+",
        "pkce.code.challenge.method": "S256"
      },
      "authenticationFlowBindingOverrides": {},
      "fullScopeAllowed": false,
      "nodeReRegistrationTimeout": 0,
      "protocolMappers": [
        {
          "id": "1c3f507f-c90e-4988-a3c8-3d679302b0ee",
          "name": "locale",
          "protocol": "openid-connect",
          "protocolMapper": "oidc-usermodel-attribute-mapper",
          "consentRequired": false,
          "config": {
            "introspection.token.claim": "true",
            "userinfo.token.claim": "true",
            "user.attribute": "locale",
            "id.token.claim": "true",
            "access.token.claim": "true",
            "claim.name": "locale",
            "jsonType.label": "String"
          }
        }
      ],
      "defaultClientScopes": [
        "web-origins",
        "acr",
        "profile",
        "roles",
        "email"
      ],
      "optionalClientScopes": [
        "address",
        "phone",
        "offline_access",
        "microprofile-jwt"
      ]
    }
  ],
  "clientScopes": [
    {
      "id": "4bbd4829-08d7-4250-8da7-f8a644ee347f",
      "name": "offline_access",
      "description": "OpenID Connect built-in scope: offline_access",
      "protocol": "openid-connect",
      "attributes": {
        "consent.screen.text": "${offlineAccessScopeConsentText}",
        "display.on.consent.screen": "true"
      }
    },
    {
      "id": "c273c0cc-5753-416e-8321-82a19ffde015",
      "name": "email",
      "description": "OpenID Connect built-in scope: email",
      "protocol": "openid-connect",
      "attributes": {
        "include.in.token.scope": "true",
        "display.on.consent.screen": "true",
        "consent.screen.text": "${emailScopeConsentText}"
      },
      "protocolMappers": [
        {
          "id": "a53bc1ab-ac4d-48c5-a966-c8c435296e80",
          "name": "email",
          "protocol": "openid-connect",
          "protocolMapper": "oidc-usermodel-attribute-mapper",
          "consentRequired": false,
          "config": {
            "introspection.token.claim": "true",
            "userinfo.token.claim": "true",
            "user.attribute": "email",
            "id.token.claim": "true",
            "access.token.claim": "true",
            "claim.name": "email",
            "jsonType.label": "String"
          }
        },
        {
          "id": "d46f9dfd-f6d2-441d-8a88-e23832b293ad",
          "name": "email verified",
          "protocol": "openid-connect",
          "protocolMapper": "oidc-usermodel-property-mapper",
          "consentRequired": false,
          "config": {
            "introspection.token.claim": "true",
            "userinfo.token.claim": "true",
            "user.attribute": "emailVerified",
            "id.token.claim": "true",
            "access.token.claim": "true",
            "claim.name": "email_verified",
            "jsonType.label": "boolean"
          }
        }
      ]
    },
    {
      "id": "00df4c82-6c3d-47da-b303-518f0f0bf78f",
      "name": "phone",
      "description": "OpenID Connect built-in scope: phone",
      "protocol": "openid-connect",
      "attributes": {
        "include.in.token.scope": "true",
        "display.on.consent.screen": "true",
        "consent.screen.text": "${phoneScopeConsentText}"
      },
      "protocolMappers": [
        {
          "id": "1768e7ff-d956-4dae-9cea-1ca188ba4a0a",
          "name": "phone number verified",
          "protocol": "openid-connect",
          "protocolMapper": "oidc-usermodel-attribute-mapper",
          "consentRequired": false,
          "config": {
            "introspection.token.claim": "true",
            "userinfo.token.claim": "true",
            "user.attribute": "phoneNumberVerified",
            "id.token.claim": "true",
            "access.token.claim": "true",
            "claim.name": "phone_number_verified",
            "jsonType.label": "boolean"
          }
        },
        {
          "id": "fcfb3f6a-1a0f-414f-b81a-41090f1a8c5e",
          "name": "phone number",
          "protocol": "openid-connect",
          "protocolMapper": "oidc-usermodel-attribute-mapper",
          "consentRequired": false,
          "config": {
            "introspection.token.claim": "true",
            "userinfo.token.claim": "true",
            "user.attribute": "phoneNumber",
            "id.token.claim": "true",
            "access.token.claim": "true",
            "claim.name": "phone_number",
            "jsonType.label": "String"
          }
        }
      ]
    },
    {
      "id": "23125618-203b-476d-a1cc-4d86b573b67f",
      "name": "role_list",
      "description": "SAML role list",
      "protocol": "saml",
      "attributes": {
        "consent.screen.text": "${samlRoleListScopeConsentText}",
        "display.on.consent.screen": "true"
      },
      "protocolMappers": [
        {
          "id": "d23598b2-9833-4465-91ab-0876f05e8b35",
          "name": "role list",
          "protocol": "saml",
          "protocolMapper": "saml-role-list-mapper",
          "consentRequired": false,
          "config": {
            "single": "false",
            "attribute.nameformat": "Basic",
            "attribute.name": "Role"
          }
        }
      ]
    },
    {
      "id": "d5dcc6c8-262c-4c4f-98fd-00312b078749",
      "name": "acr",
      "description": "OpenID Connect scope for add acr (authentication context class reference) to the token",
      "protocol": "openid-connect",
      "attributes": {
        "include.in.token.scope": "false",
        "display.on.consent.screen": "false"
      },
      "protocolMappers": [
        {
          "id": "47dba695-f08d-4d81-9a54-2d87d5692707",
          "name": "acr loa level",
          "protocol": "openid-connect",
          "protocolMapper": "oidc-acr-mapper",
          "consentRequired": false,
          "config": {
            "id.token.claim": "true",
            "introspection.token.claim": "true",
            "access.token.claim": "true"
          }
        }
      ]
    },
    {
      "id": "8e6ab693-7aec-4706-87e6-ef1a51cfd3ef",
      "name": "profile",
      "description": "OpenID Connect built-in scope: profile",
      "protocol": "openid-connect",
      "attributes": {
        "include.in.token.scope": "true",
        "display.on.consent.screen": "true",
        "consent.screen.text": "${profileScopeConsentText}"
      },
      "protocolMappers": [
        {
          "id": "05d4ac78-513c-4160-b465-91a505af5ac4",
          "name": "given name",
          "protocol": "openid-connect",
          "protocolMapper": "oidc-usermodel-attribute-mapper",
          "consentRequired": false,
          "config": {
            "introspection.token.claim": "true",
            "userinfo.token.claim": "true",
            "user.attribute": "firstName",
            "id.token.claim": "true",
            "access.token.claim": "true",
            "claim.name": "given_name",
            "jsonType.label": "String"
          }
        },
        {
          "id": "a3eac984-47f9-40d2-8641-f0bd2ce557d2",
          "name": "website",
          "protocol": "openid-connect",
          "protocolMapper": "oidc-usermodel-attribute-mapper",
          "consentRequired": false,
          "config": {
            "introspection.token.claim": "true",
            "userinfo.token.claim": "true",
            "user.attribute": "website",
            "id.token.claim": "true",
            "access.token.claim": "true",
            "claim.name": "website",
            "jsonType.label": "String"
          }
        },
        {
          "id": "c234f127-4a1b-457f-9d45-b1996562d525",
          "name": "locale",
          "protocol": "openid-connect",
          "protocolMapper": "oidc-usermodel-attribute-mapper",
          "consentRequired": false,
          "config": {
            "introspection.token.claim": "true",
            "userinfo.token.claim": "true",
            "user.attribute": "locale",
            "id.token.claim": "true",
            "access.token.claim": "true",
            "claim.name": "locale",
            "jsonType.label": "String"
          }
        },
        {
          "id": "64d6e95e-4262-40ae-bcb8-ea8d41bbe122",
          "name": "nickname",
          "protocol": "openid-connect",
          "protocolMapper": "oidc-usermodel-attribute-mapper",
          "consentRequired": false,
          "config": {
            "introspection.token.claim": "true",
            "userinfo.token.claim": "true",
            "user.attribute": "nickname",
            "id.token.claim": "true",
            "access.token.claim": "true",
            "claim.name": "nickname",
            "jsonType.label": "String"
          }
        },
        {
          "id": "7b438d75-458d-4fdb-969d-1d6c142978ac",
          "name": "zoneinfo",
          "protocol": "openid-connect",
          "protocolMapper": "oidc-usermodel-attribute-mapper",
          "consentRequired": false,
          "config": {
            "introspection.token.claim": "true",
            "userinfo.token.claim": "true",
            "user.attribute": "zoneinfo",
            "id.token.claim": "true",
            "access.token.claim": "true",
            "claim.name": "zoneinfo",
            "jsonType.label": "String"
          }
        },
        {
          "id": "6150cea0-625a-47d1-a304-af6ce140b76a",
          "name": "family name",
          "protocol": "openid-connect",
          "protocolMapper": "oidc-usermodel-attribute-mapper",
          "consentRequired": false,
          "config": {
            "introspection.token.claim": "true",
            "userinfo.token.claim": "true",
            "user.attribute": "lastName",
            "id.token.claim": "true",
            "access.token.claim": "true",
            "claim.name": "family_name",
            "jsonType.label": "String"
          }
        },
        {
          "id": "691ef7c1-2255-4830-9b77-76da67271f48",
          "name": "middle name",
          "protocol": "openid-connect",
          "protocolMapper": "oidc-usermodel-attribute-mapper",
          "consentRequired": false,
          "config": {
            "introspection.token.claim": "true",
            "userinfo.token.claim": "true",
            "user.attribute": "middleName",
            "id.token.claim": "true",
            "access.token.claim": "true",
            "claim.name": "middle_name",
            "jsonType.label": "String"
          }
        },
        {
          "id": "27072034-e936-4bc5-85ec-08ab3306e9ee",
          "name": "username",
          "protocol": "openid-connect",
          "protocolMapper": "oidc-usermodel-attribute-mapper",
          "consentRequired": false,
          "config": {
            "introspection.token.claim": "true",
            "userinfo.token.claim": "true",
            "user.attribute": "username",
            "id.token.claim": "true",
            "access.token.claim": "true",
            "claim.name": "preferred_username",
            "jsonType.label": "String"
          }
        },
        {
          "id": "8010ae89-f04f-444c-8711-751018e49bb3",
          "name": "profile",
          "protocol": "openid-connect",
          "protocolMapper": "oidc-usermodel-attribute-mapper",
          "consentRequired": false,
          "config": {
            "introspection.token.claim": "true",
            "userinfo.token.claim": "true",
            "user.attribute": "profile",
            "id.token.claim": "true",
            "access.token.claim": "true",
            "claim.name": "profile",
            "jsonType.label": "String"
          }
        },
        {
          "id": "b96a1eb4-23fc-4e1d-87c8-9dcc188e96dc",
          "name": "gender",
          "protocol": "openid-connect",
          "protocolMapper": "oidc-usermodel-attribute-mapper",
          "consentRequired": false,
          "config": {
            "introspection.token.claim": "true",
            "userinfo.token.claim": "true",
            "user.attribute": "gender",
            "id.token.claim": "true",
            "access.token.claim": "true",
            "claim.name": "gender",
            "jsonType.label": "String"
          }
        },
        {
          "id": "a9d5e198-4471-496f-87fc-e52c9690f707",
          "name": "picture",
          "protocol": "openid-connect",
          "protocolMapper": "oidc-usermodel-attribute-mapper",
          "consentRequired": false,
          "config": {
            "introspection.token.claim": "true",
            "userinfo.token.claim": "true",
            "user.attribute": "picture",
            "id.token.claim": "true",
            "access.token.claim": "true",
            "claim.name": "picture",
            "jsonType.label": "String"
          }
        },
        {
          "id": "a9915a14-2e02-4d6c-a26c-00269f2d13ed",
          "name": "birthdate",
          "protocol": "openid-connect",
          "protocolMapper": "oidc-usermodel-attribute-mapper",
          "consentRequired": false,
          "config": {
            "introspection.token.claim": "true",
            "userinfo.token.claim": "true",
            "user.attribute": "birthdate",
            "id.token.claim": "true",
            "access.token.claim": "true",
            "claim.name": "birthdate",
            "jsonType.label": "String"
          }
        },
        {
          "id": "cdf7befb-94d7-444d-aa1b-bd73629bf11b",
          "name": "updated at",
          "protocol": "openid-connect",
          "protocolMapper": "oidc-usermodel-attribute-mapper",
          "consentRequired": false,
          "config": {
            "introspection.token.claim": "true",
            "userinfo.token.claim": "true",
            "user.attribute": "updatedAt",
            "id.token.claim": "true",
            "access.token.claim": "true",
            "claim.name": "updated_at",
            "jsonType.label": "long"
          }
        },
        {
          "id": "5bf7da1d-2764-4882-80cc-2ecb3932673f",
          "name": "full name",
          "protocol": "openid-connect",
          "protocolMapper": "oidc-full-name-mapper",
          "consentRequired": false,
          "config": {
            "id.token.claim": "true",
            "introspection.token.claim": "true",
            "access.token.claim": "true",
            "userinfo.token.claim": "true"
          }
        }
      ]
    },
    {
      "id": "ed3a0ddf-21e5-4566-bc45-285620d51ab1",
      "name": "roles",
      "description": "OpenID Connect scope for add user roles to the access token",
      "protocol": "openid-connect",
      "attributes": {
        "include.in.token.scope": "false",
        "display.on.consent.screen": "true",
        "consent.screen.text": "${rolesScopeConsentText}"
      },
      "protocolMappers": [
        {
          "id": "c0f894fe-a004-49c5-83d6-e866ecf48013",
          "name": "realm roles",
          "protocol": "openid-connect",
          "protocolMapper": "oidc-usermodel-realm-role-mapper",
          "consentRequired": false,
          "config": {
            "introspection.token.claim": "true",
            "multivalued": "true",
            "user.attribute": "foo",
            "access.token.claim": "true",
            "claim.name": "realm_access.roles",
            "jsonType.label": "String"
          }
        },
        {
          "id": "1bf0fc66-55bd-4bd1-b631-7032331ff706",
          "name": "client roles",
          "protocol": "openid-connect",
          "protocolMapper": "oidc-usermodel-client-role-mapper",
          "consentRequired": false,
          "config": {
            "introspection.token.claim": "true",
            "multivalued": "true",
            "user.attribute": "foo",
            "access.token.claim": "true",
            "claim.name": "resource_access.${client_id}.roles",
            "jsonType.label": "String"
          }
        },
        {
          "id": "dd92472f-b8b9-4a59-b5dc-aef7b6ad1790",
          "name": "audience resolve",
          "protocol": "openid-connect",
          "protocolMapper": "oidc-audience-resolve-mapper",
          "consentRequired": false,
          "config": {
            "introspection.token.claim": "true",
            "access.token.claim": "true"
          }
        }
      ]
    },
    {
      "id": "86ce7167-2536-41c2-96e8-5c3a239dcdd1",
      "name": "microprofile-jwt",
      "description": "Microprofile - JWT built-in scope",
      "protocol": "openid-connect",
      "attributes": {
        "include.in.token.scope": "true",
        "display.on.consent.screen": "false"
      },
      "protocolMappers": [
        {
          "id": "87621ca4-1b45-4b22-8208-6c11c3aab7ad",
          "name": "upn",
          "protocol": "openid-connect",
          "protocolMapper": "oidc-usermodel-attribute-mapper",
          "consentRequired": false,
          "config": {
            "introspection.token.claim": "true",
            "userinfo.token.claim": "true",
            "user.attribute": "username",
            "id.token.claim": "true",
            "access.token.claim": "true",
            "claim.name": "upn",
            "jsonType.label": "String"
          }
        },
        {
          "id": "2896b858-dca5-4cdf-ab2c-1d57eb26ff62",
          "name": "groups",
          "protocol": "openid-connect",
          "protocolMapper": "oidc-usermodel-realm-role-mapper",
          "consentRequired": false,
          "config": {
            "introspection.token.claim": "true",
            "multivalued": "true",
            "user.attribute": "foo",
            "id.token.claim": "true",
            "access.token.claim": "true",
            "claim.name": "groups",
            "jsonType.label": "String"
          }
        }
      ]
    },
    {
      "id": "d15795ac-7408-4c37-b8c7-40e9dd62f00e",
      "name": "web-origins",
      "description": "OpenID Connect scope for add allowed web origins to the access token",
      "protocol": "openid-connect",
      "attributes": {
        "include.in.token.scope": "false",
        "display.on.consent.screen": "false",
        "consent.screen.text": ""
      },
      "protocolMappers": [
        {
          "id": "315930f0-d204-4ebc-8de4-9a5261c0930c",
          "name": "allowed web origins",
          "protocol": "openid-connect",
          "protocolMapper": "oidc-allowed-origins-mapper",
          "consentRequired": false,
          "config": {
            "introspection.token.claim": "true",
            "access.token.claim": "true"
          }
        }
      ]
    },
    {
      "id": "99b91fdb-6704-4103-aad9-980d73d06c58",
      "name": "address",
      "description": "OpenID Connect built-in scope: address",
      "protocol": "openid-connect",
      "attributes": {
        "include.in.token.scope": "true",
        "display.on.consent.screen": "true",
        "consent.screen.text": "${addressScopeConsentText}"
      },
      "protocolMappers": [
        {
          "id": "04a1d925-667f-4048-b7ce-4ebc31332e4e",
          "name": "address",
          "protocol": "openid-connect",
          "protocolMapper": "oidc-address-mapper",
          "consentRequired": false,
          "config": {
            "user.attribute.formatted": "formatted",
            "user.attribute.country": "country",
            "introspection.token.claim": "true",
            "user.attribute.postal_code": "postal_code",
            "userinfo.token.claim": "true",
            "user.attribute.street": "street",
            "id.token.claim": "true",
            "user.attribute.region": "region",
            "access.token.claim": "true",
            "user.attribute.locality": "locality"
          }
        }
      ]
    }
  ],
  "defaultDefaultClientScopes": [
    "role_list",
    "profile",
    "email",
    "roles",
    "web-origins",
    "acr"
  ],
  "defaultOptionalClientScopes": [
    "offline_access",
    "address",
    "phone",
    "microprofile-jwt"
  ],
  "browserSecurityHeaders": {
    "contentSecurityPolicyReportOnly": "",
    "xContentTypeOptions": "nosniff",
    "referrerPolicy": "no-referrer",
    "xRobotsTag": "none",
    "xFrameOptions": "SAMEORIGIN",
    "contentSecurityPolicy": "frame-src 'self'; frame-ancestors 'self'; object-src 'none';",
    "xXSSProtection": "1; mode=block",
    "strictTransportSecurity": "max-age=31536000; includeSubDomains"
  },
  "smtpServer": {},
  "eventsEnabled": false,
  "eventsListeners": [
    "jboss-logging"
  ],
  "enabledEventTypes": [],
  "adminEventsEnabled": false,
  "adminEventsDetailsEnabled": false,
  "identityProviders": [],
  "identityProviderMappers": [],
  "components": {
    "org.keycloak.services.clientregistration.policy.ClientRegistrationPolicy": [
      {
        "id": "99b85915-22d7-4cb4-96b0-8e7d8c6a2f2f",
        "name": "Consent Required",
        "providerId": "consent-required",
        "subType": "anonymous",
        "subComponents": {},
        "config": {}
      },
      {
        "id": "5dcf45d8-8327-466e-9b33-733fdc6d21bc",
        "name": "Allowed Protocol Mapper Types",
        "providerId": "allowed-protocol-mappers",
        "subType": "authenticated",
        "subComponents": {},
        "config": {
          "allowed-protocol-mapper-types": [
            "oidc-full-name-mapper",
            "saml-user-attribute-mapper",
            "saml-user-property-mapper",
            "oidc-usermodel-attribute-mapper",
            "oidc-address-mapper",
            "oidc-usermodel-property-mapper",
            "oidc-sha256-pairwise-sub-mapper",
            "saml-role-list-mapper"
          ]
        }
      },
      {
        "id": "0a465d36-92de-41d5-9cf8-2ce290407c48",
        "name": "Allowed Client Scopes",
        "providerId": "allowed-client-templates",
        "subType": "authenticated",
        "subComponents": {},
        "config": {
          "allow-default-scopes": [
            "true"
          ]
        }
      },
      {
        "id": "042c7b28-351a-4e1e-942f-b597fbd7cb61",
        "name": "Allowed Protocol Mapper Types",
        "providerId": "allowed-protocol-mappers",
        "subType": "anonymous",
        "subComponents": {},
        "config": {
          "allowed-protocol-mapper-types": [
            "oidc-usermodel-property-mapper",
            "oidc-full-name-mapper",
            "saml-user-property-mapper",
            "saml-role-list-mapper",
            "oidc-address-mapper",
            "oidc-usermodel-attribute-mapper",
            "saml-user-attribute-mapper",
            "oidc-sha256-pairwise-sub-mapper"
          ]
        }
      },
      {
        "id": "1b8d0214-b8a3-4c8a-bf90-bc31b26bf460",
        "name": "Max Clients Limit",
        "providerId": "max-clients",
        "subType": "anonymous",
        "subComponents": {},
        "config": {
          "max-clients": [
            "200"
          ]
        }
      },
      {
        "id": "c514d6ec-a25c-419c-85bb-0458ca72bbca",
        "name": "Full Scope Disabled",
        "providerId": "scope",
        "subType": "anonymous",
        "subComponents": {},
        "config": {}
      },
      {
        "id": "a051d2fd-1772-4548-b900-b251eef03aec",
        "name": "Trusted Hosts",
        "providerId": "trusted-hosts",
        "subType": "anonymous",
        "subComponents": {},
        "config": {
          "host-sending-registration-request-must-match": [
            "true"
          ],
          "client-uris-must-match": [
            "true"
          ]
        }
      },
      {
        "id": "163b4627-9975-4373-8d6f-e3ec91edaaba",
        "name": "Allowed Client Scopes",
        "providerId": "allowed-client-templates",
        "subType": "anonymous",
        "subComponents": {},
        "config": {
          "allow-default-scopes": [
            "true"
          ]
        }
      }
    ],
    "org.keycloak.keys.KeyProvider": [
      {
        "id": "a446b796-911c-4b53-9dbe-0a6aeef084a2",
        "name": "aes-generated",
        "providerId": "aes-generated",
        "subComponents": {},
        "config": {
          "priority": [
            "100"
          ]
        }
      },
      {
        "id": "18933e6c-488b-4d86-9916-02b6cf66f8e7",
        "name": "rsa-generated",
        "providerId": "rsa-generated",
        "subComponents": {},
        "config": {
          "priority": [
            "100"
          ]
        }
      },
      {
        "id": "a616f8ab-dde6-4664-bb8c-3d740547fb48",
        "name": "hmac-generated-hs512",
        "providerId": "hmac-generated",
        "subComponents": {},
        "config": {
          "priority": [
            "100"
          ],
          "algorithm": [
            "HS512"
          ]
        }
      },
      {
        "id": "04acd9e7-7656-4f3b-9fc0-d6be2f58a2bf",
        "name": "rsa-enc-generated",
        "providerId": "rsa-enc-generated",
        "subComponents": {},
        "config": {
          "priority": [
            "100"
          ],
          "algorithm": [
            "RSA-OAEP"
          ]
        }
      }
    ]
  },
  "internationalizationEnabled": false,
  "supportedLocales": [],
  "authenticationFlows": [
    {
      "id": "a3c45e53-85bc-4de8-b451-82948e91b987",
      "alias": "Account verification options",
      "description": "Method with which to verity the existing account",
      "providerId": "basic-flow",
      "topLevel": false,
      "builtIn": true,
      "authenticationExecutions": [
        {
          "authenticator": "idp-email-verification",
          "authenticatorFlow": false,
          "requirement": "ALTERNATIVE",
          "priority": 10,
          "autheticatorFlow": false,
          "userSetupAllowed": false
        },
        {
          "authenticatorFlow": true,
          "requirement": "ALTERNATIVE",
          "priority": 20,
          "autheticatorFlow": true,
          "flowAlias": "Verify Existing Account by Re-authentication",
          "userSetupAllowed": false
        }
      ]
    },
    {
      "id": "a9c19401-8403-4565-b3a7-c17945756da9",
      "alias": "Browser - Conditional OTP",
      "description": "Flow to determine if the OTP is required for the authentication",
      "providerId": "basic-flow",
      "topLevel": false,
      "builtIn": true,
      "authenticationExecutions": [
        {
          "authenticator": "conditional-user-configured",
          "authenticatorFlow": false,
          "requirement": "REQUIRED",
          "priority": 10,
          "autheticatorFlow": false,
          "userSetupAllowed": false
        },
        {
          "authenticator": "auth-otp-form",
          "authenticatorFlow": false,
          "requirement": "REQUIRED",
          "priority": 20,
          "autheticatorFlow": false,
          "userSetupAllowed": false
        }
      ]
    },
    {
      "id": "c1cda819-da6e-4463-a56d-6463446a75d2",
      "alias": "Direct Grant - Conditional OTP",
      "description": "Flow to determine if the OTP is required for the authentication",
      "providerId": "basic-flow",
      "topLevel": false,
      "builtIn": true,
      "authenticationExecutions": [
        {
          "authenticator": "conditional-user-configured",
          "authenticatorFlow": false,
          "requirement": "REQUIRED",
          "priority": 10,
          "autheticatorFlow": false,
          "userSetupAllowed": false
        },
        {
          "authenticator": "direct-grant-validate-otp",
          "authenticatorFlow": false,
          "requirement": "REQUIRED",
          "priority": 20,
          "autheticatorFlow": false,
          "userSetupAllowed": false
        }
      ]
    },
    {
      "id": "57486901-8bee-48ac-ba9e-d6f5ceb64215",
      "alias": "First broker login - Conditional OTP",
      "description": "Flow to determine if the OTP is required for the authentication",
      "providerId": "basic-flow",
      "topLevel": false,
      "builtIn": true,
      "authenticationExecutions": [
        {
          "authenticator": "conditional-user-configured",
          "authenticatorFlow": false,
          "requirement": "REQUIRED",
          "priority": 10,
          "autheticatorFlow": false,
          "userSetupAllowed": false
        },
        {
          "authenticator": "auth-otp-form",
          "authenticatorFlow": false,
          "requirement": "REQUIRED",
          "priority": 20,
          "autheticatorFlow": false,
          "userSetupAllowed": false
        }
      ]
    },
    {
      "id": "9ee7da48-2b88-4c2b-9d14-509b7a1a98a6",
      "alias": "Handle Existing Account",
      "description": "Handle what to do if there is existing account with same email/username like authenticated identity provider",
      "providerId": "basic-flow",
      "topLevel": false,
      "builtIn": true,
      "authenticationExecutions": [
        {
          "authenticator": "idp-confirm-link",
          "authenticatorFlow": false,
          "requirement": "REQUIRED",
          "priority": 10,
          "autheticatorFlow": false,
          "userSetupAllowed": false
        },
        {
          "authenticatorFlow": true,
          "requirement": "REQUIRED",
          "priority": 20,
          "autheticatorFlow": true,
          "flowAlias": "Account verification options",
          "userSetupAllowed": false
        }
      ]
    },
    {
      "id": "de023ea7-b2ed-45e9-af41-47bd7a874e8b",
      "alias": "Reset - Conditional OTP",
      "description": "Flow to determine if the OTP should be reset or not. Set to REQUIRED to force.",
      "providerId": "basic-flow",
      "topLevel": false,
      "builtIn": true,
      "authenticationExecutions": [
        {
          "authenticator": "conditional-user-configured",
          "authenticatorFlow": false,
          "requirement": "REQUIRED",
          "priority": 10,
          "autheticatorFlow": false,
          "userSetupAllowed": false
        },
        {
          "authenticator": "reset-otp",
          "authenticatorFlow": false,
          "requirement": "REQUIRED",
          "priority": 20,
          "autheticatorFlow": false,
          "userSetupAllowed": false
        }
      ]
    },
    {
      "id": "3821cf9b-b4a7-4321-b891-ebcb2eaa845b",
      "alias": "User creation or linking",
      "description": "Flow for the existing/non-existing user alternatives",
      "providerId": "basic-flow",
      "topLevel": false,
      "builtIn": true,
      "authenticationExecutions": [
        {
          "authenticatorConfig": "create unique user config",
          "authenticator": "idp-create-user-if-unique",
          "authenticatorFlow": false,
          "requirement": "ALTERNATIVE",
          "priority": 10,
          "autheticatorFlow": false,
          "userSetupAllowed": false
        },
        {
          "authenticatorFlow": true,
          "requirement": "ALTERNATIVE",
          "priority": 20,
          "autheticatorFlow": true,
          "flowAlias": "Handle Existing Account",
          "userSetupAllowed": false
        }
      ]
    },
    {
      "id": "5118ea39-16f4-4ae7-adeb-015148c51e40",
      "alias": "Verify Existing Account by Re-authentication",
      "description": "Reauthentication of existing account",
      "providerId": "basic-flow",
      "topLevel": false,
      "builtIn": true,
      "authenticationExecutions": [
        {
          "authenticator": "idp-username-password-form",
          "authenticatorFlow": false,
          "requirement": "REQUIRED",
          "priority": 10,
          "autheticatorFlow": false,
          "userSetupAllowed": false
        },
        {
          "authenticatorFlow": true,
          "requirement": "CONDITIONAL",
          "priority": 20,
          "autheticatorFlow": true,
          "flowAlias": "First broker login - Conditional OTP",
          "userSetupAllowed": false
        }
      ]
    },
    {
      "id": "d1265505-24cd-47f0-a6f8-9aae98c1eab2",
      "alias": "browser",
      "description": "browser based authentication",
      "providerId": "basic-flow",
      "topLevel": true,
      "builtIn": true,
      "authenticationExecutions": [
        {
          "authenticator": "auth-cookie",
          "authenticatorFlow": false,
          "requirement": "ALTERNATIVE",
          "priority": 10,
          "autheticatorFlow": false,
          "userSetupAllowed": false
        },
        {
          "authenticator": "auth-spnego",
          "authenticatorFlow": false,
          "requirement": "DISABLED",
          "priority": 20,
          "autheticatorFlow": false,
          "userSetupAllowed": false
        },
        {
          "authenticator": "identity-provider-redirector",
          "authenticatorFlow": false,
          "requirement": "ALTERNATIVE",
          "priority": 25,
          "autheticatorFlow": false,
          "userSetupAllowed": false
        },
        {
          "authenticatorFlow": true,
          "requirement": "ALTERNATIVE",
          "priority": 30,
          "autheticatorFlow": true,
          "flowAlias": "forms",
          "userSetupAllowed": false
        }
      ]
    },
    {
      "id": "e5765948-0d1e-4316-99ad-84221af90de3",
      "alias": "clients",
      "description": "Base authentication for clients",
      "providerId": "client-flow",
      "topLevel": true,
      "builtIn": true,
      "authenticationExecutions": [
        {
          "authenticator": "client-secret",
          "authenticatorFlow": false,
          "requirement": "ALTERNATIVE",
          "priority": 10,
          "autheticatorFlow": false,
          "userSetupAllowed": false
        },
        {
          "authenticator": "client-jwt",
          "authenticatorFlow": false,
          "requirement": "ALTERNATIVE",
          "priority": 20,
          "autheticatorFlow": false,
          "userSetupAllowed": false
        },
        {
          "authenticator": "client-secret-jwt",
          "authenticatorFlow": false,
          "requirement": "ALTERNATIVE",
          "priority": 30,
          "autheticatorFlow": false,
          "userSetupAllowed": false
        },
        {
          "authenticator": "client-x509",
          "authenticatorFlow": false,
          "requirement": "ALTERNATIVE",
          "priority": 40,
          "autheticatorFlow": false,
          "userSetupAllowed": false
        }
      ]
    },
    {
      "id": "451f6c1e-ccc6-405b-9127-fcbf835fedd8",
      "alias": "direct grant",
      "description": "OpenID Connect Resource Owner Grant",
      "providerId": "basic-flow",
      "topLevel": true,
      "builtIn": true,
      "authenticationExecutions": [
        {
          "authenticator": "direct-grant-validate-username",
          "authenticatorFlow": false,
          "requirement": "REQUIRED",
          "priority": 10,
          "autheticatorFlow": false,
          "userSetupAllowed": false
        },
        {
          "authenticator": "direct-grant-validate-password",
          "authenticatorFlow": false,
          "requirement": "REQUIRED",
          "priority": 20,
          "autheticatorFlow": false,
          "userSetupAllowed": false
        },
        {
          "authenticatorFlow": true,
          "requirement": "CONDITIONAL",
          "priority": 30,
          "autheticatorFlow": true,
          "flowAlias": "Direct Grant - Conditional OTP",
          "userSetupAllowed": false
        }
      ]
    },
    {
      "id": "01e6d4e4-b98c-481b-bccf-3a631de6e40f",
      "alias": "docker auth",
      "description": "Used by Docker clients to authenticate against the IDP",
      "providerId": "basic-flow",
      "topLevel": true,
      "builtIn": true,
      "authenticationExecutions": [
        {
          "authenticator": "docker-http-basic-authenticator",
          "authenticatorFlow": false,
          "requirement": "REQUIRED",
          "priority": 10,
          "autheticatorFlow": false,
          "userSetupAllowed": false
        }
      ]
    },
    {
      "id": "dd37f2ae-5f62-43c2-ac62-953605124983",
      "alias": "first broker login",
      "description": "Actions taken after first broker login with identity provider account, which is not yet linked to any Keycloak account",
      "providerId": "basic-flow",
      "topLevel": true,
      "builtIn": true,
      "authenticationExecutions": [
        {
          "authenticatorConfig": "review profile config",
          "authenticator": "idp-review-profile",
          "authenticatorFlow": false,
          "requirement": "REQUIRED",
          "priority": 10,
          "autheticatorFlow": false,
          "userSetupAllowed": false
        },
        {
          "authenticatorFlow": true,
          "requirement": "REQUIRED",
          "priority": 20,
          "autheticatorFlow": true,
          "flowAlias": "User creation or linking",
          "userSetupAllowed": false
        }
      ]
    },
    {
      "id": "8a1f87aa-1c35-4794-84d1-42c3f4822f5f",
      "alias": "forms",
      "description": "Username, password, otp and other auth forms.",
      "providerId": "basic-flow",
      "topLevel": false,
      "builtIn": true,
      "authenticationExecutions": [
        {
          "authenticator": "auth-username-password-form",
          "authenticatorFlow": false,
          "requirement": "REQUIRED",
          "priority": 10,
          "autheticatorFlow": false,
          "userSetupAllowed": false
        },
        {
          "authenticatorFlow": true,
          "requirement": "CONDITIONAL",
          "priority": 20,
          "autheticatorFlow": true,
          "flowAlias": "Browser - Conditional OTP",
          "userSetupAllowed": false
        }
      ]
    },
    {
      "id": "b84062f0-34f1-437f-b17d-7b1f0d2be518",
      "alias": "registration",
      "description": "registration flow",
      "providerId": "basic-flow",
      "topLevel": true,
      "builtIn": true,
      "authenticationExecutions": [
        {
          "authenticator": "registration-page-form",
          "authenticatorFlow": true,
          "requirement": "REQUIRED",
          "priority": 10,
          "autheticatorFlow": true,
          "flowAlias": "registration form",
          "userSetupAllowed": false
        }
      ]
    },
    {
      "id": "2ff474c2-8c8c-4775-ba71-c432ef04cf1d",
      "alias": "registration form",
      "description": "registration form",
      "providerId": "form-flow",
      "topLevel": false,
      "builtIn": true,
      "authenticationExecutions": [
        {
          "authenticator": "registration-user-creation",
          "authenticatorFlow": false,
          "requirement": "REQUIRED",
          "priority": 20,
          "autheticatorFlow": false,
          "userSetupAllowed": false
        },
        {
          "authenticator": "registration-password-action",
          "authenticatorFlow": false,
          "requirement": "REQUIRED",
          "priority": 50,
          "autheticatorFlow": false,
          "userSetupAllowed": false
        },
        {
          "authenticator": "registration-recaptcha-action",
          "authenticatorFlow": false,
          "requirement": "DISABLED",
          "priority": 60,
          "autheticatorFlow": false,
          "userSetupAllowed": false
        },
        {
          "authenticator": "registration-terms-and-conditions",
          "authenticatorFlow": false,
          "requirement": "DISABLED",
          "priority": 70,
          "autheticatorFlow": false,
          "userSetupAllowed": false
        }
      ]
    },
    {
      "id": "9c4c549b-f87e-435e-9389-4c05293d6a98",
      "alias": "reset credentials",
      "description": "Reset credentials for a user if they forgot their password or something",
      "providerId": "basic-flow",
      "topLevel": true,
      "builtIn": true,
      "authenticationExecutions": [
        {
          "authenticator": "reset-credentials-choose-user",
          "authenticatorFlow": false,
          "requirement": "REQUIRED",
          "priority": 10,
          "autheticatorFlow": false,
          "userSetupAllowed": false
        },
        {
          "authenticator": "reset-credential-email",
          "authenticatorFlow": false,
          "requirement": "REQUIRED",
          "priority": 20,
          "autheticatorFlow": false,
          "userSetupAllowed": false
        },
        {
          "authenticator": "reset-password",
          "authenticatorFlow": false,
          "requirement": "REQUIRED",
          "priority": 30,
          "autheticatorFlow": false,
          "userSetupAllowed": false
        },
        {
          "authenticatorFlow": true,
          "requirement": "CONDITIONAL",
          "priority": 40,
          "autheticatorFlow": true,
          "flowAlias": "Reset - Conditional OTP",
          "userSetupAllowed": false
        }
      ]
    },
    {
      "id": "d58cb661-1a61-4479-84f3-b4d8354decf9",
      "alias": "saml ecp",
      "description": "SAML ECP Profile Authentication Flow",
      "providerId": "basic-flow",
      "topLevel": true,
      "builtIn": true,
      "authenticationExecutions": [
        {
          "authenticator": "http-basic-authenticator",
          "authenticatorFlow": false,
          "requirement": "REQUIRED",
          "priority": 10,
          "autheticatorFlow": false,
          "userSetupAllowed": false
        }
      ]
    }
  ],
  "authenticatorConfig": [
    {
      "id": "a7eddc19-fa1b-4d8d-985c-b393dec30716",
      "alias": "create unique user config",
      "config": {
        "require.password.update.after.registration": "false"
      }
    },
    {
      "id": "e6217a65-3117-4209-8e2b-423dc0bea6eb",
      "alias": "review profile config",
      "config": {
        "update.profile.on.first.login": "missing"
      }
    }
  ],
  "requiredActions": [
    {
      "alias": "CONFIGURE_TOTP",
      "name": "Configure OTP",
      "providerId": "CONFIGURE_TOTP",
      "enabled": true,
      "defaultAction": false,
      "priority": 10,
      "config": {}
    },
    {
      "alias": "TERMS_AND_CONDITIONS",
      "name": "Terms and Conditions",
      "providerId": "TERMS_AND_CONDITIONS",
      "enabled": false,
      "defaultAction": false,
      "priority": 20,
      "config": {}
    },
    {
      "alias": "UPDATE_PASSWORD",
      "name": "Update Password",
      "providerId": "UPDATE_PASSWORD",
      "enabled": true,
      "defaultAction": false,
      "priority": 30,
      "config": {}
    },
    {
      "alias": "UPDATE_PROFILE",
      "name": "Update Profile",
      "providerId": "UPDATE_PROFILE",
      "enabled": true,
      "defaultAction": false,
      "priority": 40,
      "config": {}
    },
    {
      "alias": "VERIFY_EMAIL",
      "name": "Verify Email",
      "providerId": "VERIFY_EMAIL",
      "enabled": true,
      "defaultAction": false,
      "priority": 50,
      "config": {}
    },
    {
      "alias": "delete_account",
      "name": "Delete Account",
      "providerId": "delete_account",
      "enabled": false,
      "defaultAction": false,
      "priority": 60,
      "config": {}
    },
    {
      "alias": "webauthn-register",
      "name": "Webauthn Register",
      "providerId": "webauthn-register",
      "enabled": true,
      "defaultAction": false,
      "priority": 70,
      "config": {}
    },
    {
      "alias": "webauthn-register-passwordless",
      "name": "Webauthn Register Passwordless",
      "providerId": "webauthn-register-passwordless",
      "enabled": true,
      "defaultAction": false,
      "priority": 80,
      "config": {}
    },
    {
      "alias": "VERIFY_PROFILE",
      "name": "Verify Profile",
      "providerId": "VERIFY_PROFILE",
      "enabled": true,
      "defaultAction": false,
      "priority": 90,
      "config": {}
    },
    {
      "alias": "update_user_locale",
      "name": "Update User Locale",
      "providerId": "update_user_locale",
      "enabled": true,
      "defaultAction": false,
      "priority": 1000,
      "config": {}
    }
  ],
  "browserFlow": "browser",
  "registrationFlow": "registration",
  "directGrantFlow": "direct grant",
  "resetCredentialsFlow": "reset credentials",
  "clientAuthenticationFlow": "clients",
  "dockerAuthenticationFlow": "docker auth",
  "firstBrokerLoginFlow": "first broker login",
  "attributes": {
    "cibaBackchannelTokenDeliveryMode": "poll",
    "cibaExpiresIn": "120",
    "cibaAuthRequestedUserHint": "login_hint",
    "oauth2DeviceCodeLifespan": "600",
    "oauth2DevicePollingInterval": "5",
    "clientOfflineSessionMaxLifespan": "0",
    "clientSessionIdleTimeout": "0",
    "parRequestUriLifespan": "60",
    "clientSessionMaxLifespan": "0",
    "clientOfflineSessionIdleTimeout": "0",
    "cibaInterval": "5",
    "realmReusableOtpCode": "false"
  },
  "keycloakVersion": "24.0.1",
  "userManagedAccessAllowed": false,
  "clientProfiles": {
    "profiles": []
  },
  "clientPolicies": {
    "policies": []
  }
}