{
  "kind": "collectionType",
  "collectionName": "features",
  "info": {
    "singularName": "feature",
    "pluralName": "features",
    "displayName": "Feature",
    "description": ""
  },
  "options": {
    "draftAndPublish": true
  },
  "pluginOptions": {},
  "attributes": {
    "title": {
      "type": "string",
      "required": true
    },
    "description": {
      "type": "text"
    },
    "icon": {
      "type": "string",
      "required": true,
      "default": "Sparkles"
    }
  }
}
